{"cameraMode":{"drawMode":0,"name":"Shaded","section":"Shading Mode"},"sceneLighting":false,"audioPlay":false,"sceneViewState":{"showFog":true,"showMaterialUpdate":false,"showSkybox":false,"showFlares":true,"showImageEffects":true,"showParticleSystems":true},"in2DMode":false,"pivot":{"x":-2.9849600791931154,"y":-1.9888367652893067,"z":4.815093517303467},"rotation":{"x":-0.2614259421825409,"y":0.6463282108306885,"z":-0.25172722339630129,"w":-0.6712300181388855},"size":12.631046295166016,"orthographic":false}